MANIFEST.in
setup.cfg
setup.py
ringo_comment/__init__.py
ringo_comment/model.py
ringo_comment/views.py
ringo_comment.egg-info/PKG-INFO
ringo_comment.egg-info/SOURCES.txt
ringo_comment.egg-info/dependency_links.txt
ringo_comment.egg-info/entry_points.txt
ringo_comment.egg-info/not-zip-safe
ringo_comment.egg-info/requires.txt
ringo_comment.egg-info/top_level.txt
ringo_comment/lib/__init__.py
ringo_comment/lib/renderer.py
ringo_comment/locale/ringo_comment.pot
ringo_comment/locale/de/LC_MESSAGES/ringo_comment.po
ringo_comment/templates/comments.mako