Metadata-Version: 1.0
Name: ringo-comment
Version: 1.1
Summary: Comment extension for the Ringo framework
Home-page: https://bitbucket.org/ti/ringo_comment
Author: Torsten Irländer
Author-email: torsten.irlaender@googlemail.com
License: GPL
Keywords: ringo extension
Platform: UNKNOWN
